{
   "common": [
      "consent",
      "status",
      "progress",
      "recordeddate",
      "responseid",
      "responseset",
      "name",
      "externaldatareference",
      "email",
      "recipientlastname",
      "recipientfirstname",
      "recipientemail",
      "externalreference",
      "distributionchannel",
      "userlanguage",
      "ipaddress",
      "locationlatitude",
      "locationlongitude",
      "locationaccuracy",
      "id",
      "ethnic_background",
      "uni",
      "uni_name",
      "university"
   ],
   "site_spec": {
      "Albania_Jasini": [
         "livingsituation_13_text",
         "religion_10_text",
         "sexual_orientation_7_text",
         "migration_background_3_text",
         "q75"
      ],
      "Australia_Anderson": [
         "q1",
         "livingsituation_13_text",
         "religion_10_text",
         "sexual_orientation_7_text",
         "migration_background_3_text"
      ],
      "Australia_Dar_Nimrod": [
         "livingsituation_13_text",
         "religion_10_text",
         "sexual_orientation_7_text",
         "migration_background_3_text"
      ],
      "Belgium_Vangrootel": [
         "q155",
         "livingsituation_13_text",
         "religion_10_text",
         "sexual_orientation_7_text",
         "citizenship_4_text",
         "migration_background_3_text"
      ],
      "Bolivia_Schulmeyer": [
         "livingsituation_13_text",
         "religion_10_text",
         "sexual_orientation_7_text",
         "migration_background_3_text",
         "father_cultural_ori",
         "mother_cultural_ori",
         "own_cultural_origin",
         "culture_div_labour_1",
         "culture_div_labour_2"
      ],
      "Canada_Block": [
         "q76",
         "q75",
         "livingsituation_13_text",
         "religion_10_text",
         "sexual_orientation_7_text",
         "migration_background_3_text",
         "q78"
      ],
      "China_Zhao": [
         "q1",
         "q78",
         "q7",
         "q12",
         "q18",
         "q25",
         "q51",
         "livingsituation_text",
         "religion_text",
         "sexual_orientation_text",
         "migration_background_text",
         "q75",
         "q77"
      ],
      "Colombia_Meister": [
         "q80",
         "livingsituation_13_text",
         "religion_10_text",
         "sexual_orientation_7_text",
         "migration_background_3_text",
         "livingsituation_13_text - topics",
         "sexual_orientation_7_text - topics"
      ],
      "CostaRica_Castro": [
         "livingsituation_13_text",
         "religion_10_text",
         "sexual_orientation_7_text",
         "migration_background_3_text"
      ],
      "Croatia_Franc": [
         "livingsituation_13_text",
         "religion_10_text",
         "sexual_orientation_7_text",
         "migration_background_3_text",
         "q78"
      ],
      "Ethiopia_Lemma": [
         "livingsituation_13_text",
         "religion_10_text",
         "sexual_orientation_7_text",
         "migration_background_3_text"
      ],
      "France_Regner": [
         "livingsituation_13_text",
         "religion_10_text",
         "sexual_orientation_7_text",
         "migration_background_3_text"
      ],
      "Germany_Hoppe": [
         "livingsituation_13_text",
         "religion_10_text",
         "sexual_orientation_7_text",
         "migration_background_2_text",
         "migration_background_3_text",
         "part_germany"
      ],
      "Germany_Steffens": [
         "q79",
         "livingsituation_13_text",
         "religion_10_text",
         "sexual_orientation_7_text",
         "migration_background_2_text",
         "migration_background_3_text",
         "q84",
         "q86",
         "q87",
         "q88",
         "q89",
         "q90_1",
         "q90_2",
         "q90_3",
         "q90_4",
         "q91_1",
         "q91_2",
         "q91_3",
         "q91_4",
         "q91_5",
         "q91_6",
         "q91_7",
         "q91_8",
         "q81",
         "q80",
         "q82",
         "q83_1",
         "q83_2",
         "q83_3",
         "q83_4",
         "q83_5",
         "q83_6",
         "q83_7",
         "q83_8",
         "q92"
      ],
      "Kansas_Xian": [
         "q77",
         "q1",
         "q7",
         "q12",
         "q18",
         "q25",
         "q51",
         "livingsituation_text",
         "religion_text",
         "sexual_orientation_text",
         "migration_background_text",
         "q78",
         "q78_text"
      ],
      "Kobe_Keiko": [
         "livingsituation_13_text",
         "religion_10_text",
         "sexual_orientation_7_text",
         "migration_background_3_text",
         "schoolid"
      ],
      "Lebanon_Saab": [
         "q96",
         "livingsituation_13_text",
         "course_127_text",
         "study_year_5_text",
         "q88",
         "religion_10_text",
         "q85",
         "q85_9_text",
         "sexual_orientation_7_text",
         "migration_background_3_text",
         "ethnic_background_2_text",
         "ethnic_background_10_text",
         "q82",
         "q89",
         "to what extent are y",
         "on the whole, men ma_1",
         "on the whole, men ma_2",
         "on the whole, men ma_3",
         "on the whole, men ma_4",
         "on the whole, men ma_5",
         "on the whole, men ma_6",
         "on the whole, men ma_7",
         "on the whole, men ma_8",
         "on the whole, men ma_9",
         "on the whole, men ma_10",
         "q83",
         "q83_18_text",
         "q84",
         "q86",
         "q87",
         "q92"
      ],
      "Malaysia_Selvan": [
         "livingsituation_13_text",
         "religion_10_text",
         "sexual_orientation_7_text",
         "migration_background_3_text",
         "q77",
         "q78"
      ],
      "Nagoya_Keiko": [
         "livingsituation_13_text",
         "religion_10_text",
         "sexual_orientation_7_text",
         "migration_background_3_text",
         "schoolid"
      ],
      "Netherlands_Vink": [
         "livingsituation_13_text",
         "religion_10_text",
         "sexual_orientation_7_text",
         "citizenship_4_text",
         "migration_background_3_text",
         "q136",
         "q136_2_text"
      ],
      "NewZealand_McNamara": [
         "q77",
         "livingsituation_13_text",
         "religion_10_text",
         "sexual_orientation_7_text",
         "migration_background_3_text",
         "ethnic_background_do_1",
         "ethnic_background_do_2",
         "ethnic_background_do_12",
         "ethnic_background_do_14",
         "ethnic_background_do_13",
         "ethnic_background_do_3",
         "ethnic_background_do_4",
         "ethnic_background_do_5",
         "ethnic_background_do_6",
         "ethnic_background_do_7",
         "ethnic_background_do_9"
      ],
      "Norway_Olsson": [
         "livingsituation_13_text",
         "religion_10_text",
         "sexual_orientation_7_text",
         "migration_background_2_text",
         "migration_background_3_text"
      ],
      "Pakistan_Bushra": [
         "livingsituation_13_text",
         "religion_10_text",
         "sexual_orientation_7_text",
         "migration_background_3_text"
      ],
      "Serbia_Zezelj": [
         "livingsituation_13_text",
         "religion_10_text",
         "sexual_orientation_7_text",
         "migration_background_3_text",
         "q77"
      ],
      "Switzerland_Nikitin": [
         "livingsituation_13_text",
         "religion_10_text",
         "sexual_orientation_7_text",
         "migration_background_2_text",
         "migration_background_4_text",
         "migration_background_3_text",
         "regional_background"
      ],
      "Switzerland_Sczesny": [
         "livingsituation_13_text",
         "religion_10_text",
         "sexual_orientation_7_text",
         "migration_background_3_text",
         "q78"
      ],
      "Toronto_Hall": [
         "livingsituation_13_text",
         "religion_10_text",
         "sexual_orientation_7_text",
         "migration_background_3_text",
         "q77"
      ],
      "Turkey_Gungor": [
         "livingsituation_13_text",
         "religion_10_text",
         "sexual_orientation_7_text",
         "migration_background_3_text",
         "q77"
      ],
      "Turkey_Kunurgu": [
         "livingsituation_13_text",
         "religion_10_text",
         "sexual_orientation_7_text",
         "migration_background_3_text",
         "q77"
      ],
      "UMass_Rodriguez": [
         "q81",
         "q78",
         "livingsituation_13_text",
         "religion_10_text",
         "sexual_orientation_7_text",
         "migration_background_3_text",
         "q79"
      ],
      "USA_Devos": [
         "icf",
         "livingsituation_text",
         "religion_text",
         "sexual_orientation_text",
         "migration_background_text",
         "source",
         "site"
      ],
      "Waterloo_Bergsieker": [
         "livingsituation_13_text",
         "religion_10_text",
         "sexual_orientation_7_text",
         "migration_background_3_text",
         "type"
      ]
   }
}

