{
  "country": [
    "ALB",
    "USA",
    "AUS",
    "BEL",
    "BOL",
    "CAN",
    "CHL",
    "CHN",
    "COL",
    "CRI",
    "HRV",
    "CZE",
    "ECU",
    "ETH",
    "FRA",
    "CHE",
    "DEU",
    "IND",
    "IDN",
    "IRL",
    "ITA",
    "JPN",
    "KOR",
    "XKX",
    "LBN",
    "MKD",
    "MYS",
    "NLD",
    "NZL",
    "NOR",
    "PAK",
    "POL",
    "ROU",
    "SRB",
    "SGP",
    "SVK",
    "ESP",
    "SWE",
    "TZA",
    "TUR",
    "GBR",
    "UKR"
  ],
  "site": [
    "Albania_Jasini",
    "Arizona_Croft",
    "Australia_Anderson",
    "Australia_DarNimrod",
    "Belgium_Vangrootel",
    "Bolivia_Schulmeyer",
    "Canada_Block",
    "Canada_Hall",
    "Canada_Steele",
    "Chile_Gonzalez",
    "Chile_Sirlopu",
    "China_Zhao",
    "Colombia_Lopez",
    "Colombia_Meister",
    "CostaRica_Castro",
    "Croatia_Franc",
    "Croatia_Sucic",
    "Czech_Klocova",
    "Ecuador_Orrego",
    "Ethiopia_Lemma",
    "France_Redersdorff",
    "France_Regner",
    "Geneva_Kulich",
    "Germany_Hoppe",
    "Germany_Steffens",
    "India_Rani",
    "Indonesia_Avicenna",
    "Ireland_Bosak",
    "Italy_Fridanna",
    "Italy_Maricchiolo",
    "Japan_Sakata",
    "Kansas_Xian",
    "Kobe_Keiko",
    "Korea_Choi",
    "Kosovo_Berdyna",
    "Lebanon_Saab",
    "Macedonia_Gjoneska",
    "Malaysia_Selvan",
    "Nagoya_Keiko",
    "Netherlands_Otten",
    "Netherlands_Vink",
    "NewZealand_McNamara",
    "Norway_Olsson",
    "Pakistan_Bushra",
    "Pakistan_Hassan",
    "Poland_Adamus",
    "Poland_Kosakowska",
    "Poland_Pyrkosz",
    "Romania_Birneanu",
    "Serbia_Jaksic",
    "Serbia_Zezelj",
    "Singapore_Lee",
    "Slovakia_Fedakova",
    "Spain_Gartzia",
    "Spain_Lemus",
    "Sweden_Back",
    "Switzerland_Haessler",
    "Switzerland_Nikitin",
    "Switzerland_Sczesny",
    "Tanzania_Mkamwa",
    "Turkey_Gungor",
    "Turkey_Kunurgu",
    "UK_Kirby",
    "USA_Bosson",
    "USA_Devos",
    "USA_Diekman",
    "USA_Germano",
    "USA_Rivera-Rodriguez",
    "Ukraine_Kozytska",
    "Waterloo_Bergsieker"
  ],
  "gender": [
    "Male",
    "NA",
    "Female",
    "Neither best reflects my identity",
    "Vrouw",
    "Man",
    "Geen van beide reflecteert mijn identiteit",
    "1",
    "2",
    "3",
    "Femme",
    "Homme",
    "Aucune de ces catégories ne décrit mon genre",
    "남성",
    "여성",
    "둘 다 나의 정체성을 잘 반영하지 못한다",
    "o\tŽenskog",
    "o\tMuškog",
    "o\tNijedno ne opisuje dobro kako se osećam u vezi sa svojim rodom",
    "Femenino",
    "Masculino",
    "Ninguna de las dos refleja mi identidad",
    "Kvinna",
    "Inget av dem",
    "male"
  ],
  "finished": [
    "NA",
    "TRUE",
    "FALSE"
  ],
  "study_year": [
    "3",
    "2",
    "5",
    "6",
    "4",
    "NA",
    "1",
    "7",
    "1st year bachelor or similar",
    "3rd year bachelor or similar",
    "2nd year bachelor or similar",
    "4th year bachelor or similar",
    "5th year + or second bachelor degree or similar",
    "1st year Masters or similar",
    "2nd year Masters or similar",
    "1e jaar bachelor of gelijkaardig",
    "2e jaar bachelor of gelijkaardig",
    "3e jaar bachelor of gelijkaardig",
    "2e jaar master of gelijkaardig",
    "1e jaar master of gelijkaardig",
    "5e of hoger bachelorjaar, tweede bachelordiploma of gelijkaardig",
    "1 ère année de Licence ou similaire",
    "2 nde année de Licence ou similaire",
    "3 ème année de Licence ou similaire",
    "1 ère année de Master",
    "2 ème année de Master",
    "2ème année de Bachelor (ou similaire)",
    "3ème année de Bachelor (ou similaire)",
    "1ère année de Bachelor (ou similaire)",
    "4ème année de Bachelor (ou similaire)",
    "5ème année et plus, ou deuxième Bachelor (ou similaire)",
    "2ème année de Bachelor (ou équivalent)",
    "3ème année de Bachelor (ou équivalent)",
    "4ème année de Bachelor (ou équivalent)",
    "5ème année et plus, ou deuxième Bachelor (ou équivalent)",
    "1ère année de Bachelor (ou équivalent)",
    "1ère année de Master (ou similaire)",
    "2ème année de Master (ou similaire)",
    "학사과정 4학년  또는 이와 유사한 상태",
    "석사과정 2학년 또는 이와 유사한 상태",
    "학사과정 2학년  또는 이와 유사한 상태",
    "석사과정 1학년 또는 이와 유사한 상태",
    "학사과정 3학년  또는 이이와 유사한 상태",
    "학사과정 1학년 또는 이와 유사한 상태",
    "학사과정 5 학년 + 또는 두 번째 학사 학위 또는 이와 유사한 상태",
    "4e jaar bachelor of gelijkaardig",
    "Prvoj master studija",
    "Prvoj osnovnih studija",
    "Drugoj master studija",
    "Trećoj osnovnih studija",
    "Četvrtoj osnovnih studija",
    "Drugoj osnovnih studija",
    "Cuarto año de grado o similar",
    "Tercer año de grado o similar",
    "Primer año de Máster o similar",
    "Segundo año de grado o similar",
    "Quinto año de grado o Segundo Grado o similar",
    "Segundo año de Máster o similar",
    "Primer año de grado o similar",
    "1a året på masternivå",
    "4e året (magisternivå)",
    "1a året på kandidatnivå",
    "3e året på kandidatnivå",
    "2a året på kandidatnivå",
    "2a året på masternivå",
    "5e året  eller mer, en andra kandidatexamen eller liknande",
    "9",
    "8",
    "3d year Masters or similar",
    "4th year Masters or similar",
    "2rd year bachelor or similar",
    "2nd year bachelor or smilar",
    "2nd year Masters or Similar"
  ],
  "citizenship": [
    "1",
    "NA",
    "Yes",
    "No, but a permanent visa",
    "No, but a student visa",
    "Other",
    "Ander, namelijk",
    "Ja",
    "Nee maar een permanent visum",
    "Nee maar een studentenvisum",
    "3",
    "4",
    "2",
    "Oui",
    "Non, mais j'ai un permis de séjour",
    "Autre",
    "Non, mais j'ai un permis d'étudiant",
    "네",
    "아니오, 그러나 학생 비자는 있다",
    "o\tDA",
    "o\tNe, ali imam studentsku vizu",
    "o\tNe, ali imam stalan boravak",
    "o\tDrugo",
    "Sí",
    "No, pero sí un permiso de estudios",
    "No, pero sí permiso de residencia permanente",
    "Nej, men permanent visum",
    "Nej, men studentvisum",
    "Annat",
    "1=Yes,",
    "3=Not, but a student visa"
  ],
  "expect_child": [
    "5",
    "4",
    "1",
    "3",
    "NA",
    "2",
    "I definitely do NOT want any children in my future.",
    "I definitely want a child/children.",
    "I most likely want a child/children.",
    "I am unsure whether I want children in my future.",
    "I already have a child/children",
    "Ik wil waarschijnlijk een kind/kinderen in de toekomst.",
    "Ik wil zeker een kind/kinderen in de toekomst.",
    "Ik ben niet zeker of ik kinderen wil in de toekomst.",
    "Ik wil zeker GEEN kinderen in de toekomst.",
    "Ik heb al een kind/kinderen.",
    "Je ne suis pas sûr(sure) de vouloir des enfants à l'avenir.",
    "Je veux absolument avoir un (ou des) enfant(s).",
    "Je voudrai certainement avoir un (ou des) enfant(s).",
    "Je ne veux absolument PAS avoir d'enfants à l'avenir.",
    "J'ai déjà un (ou des) enfant(s)",
    "나는 아마도 아이/아이들을 원할 것이다.",
    "나는 확실히 아이/아이들을 원한다.",
    "나는 미래에 아이들을 전혀 원하지 않는다.",
    "내 미래에 아이들이 있는 것을 내가 원하는지 확실하지 않다.",
    "나는 이미 아이/아이들이 있다.",
    "Sigurno želim da imam decu u budućnosti.",
    "Najverovatnije želim da imam decu u budućnosti.",
    "Nisam siguran/sigurna da li želim da imam decu u budućnosti.",
    "Već imam dete/decu.",
    "Sigurno NE ŽELIM da imam decu u budućnosti.",
    "Lo más probable es que quiera tener hijos(s)/a(s).",
    "Definitivamente quiero tener hijo(s)/a(s).",
    "Estoy inseguro/a de si quiero tener hijos/as en el futuro.",
    "Definitivamente NO quiero tener hijos/as en el futuro.",
    "Ya tengo un hijo(s)/a(s).",
    "Jag vill definitivt ha barn.",
    "Jag har redan ett eller flera barn.",
    "Jag är osäker på om jag vill ha barn i framtiden.",
    "Jag vill med största sannolikhet ha barn.",
    "Jag vill definitivt INTE ha barn i framtiden.",
    "4=I most likely want a child/children",
    "5=I definitely want a child/children",
    "3=Im unsure whether I want children in my future.",
    "1=I already have a child/children"
  ],
  "upbringing": [
    "1",
    "2",
    "3",
    "NA",
    "a city",
    "a town",
    "the countryside/ a remote place",
    "Het platteland/een afgelegen plaats",
    "Een stad",
    "Een grote stad",
    "une petite ville",
    "à la campagne / un lieu isolé",
    "une grande ville",
    "대도시",
    "중, 소도시",
    "시골/ 외딴 곳",
    "Selo",
    "Grad",
    "Manje mesto",
    "Una ciudad",
    "Un pueblo",
    "El campo/ámbito rural",
    "en småstad",
    "en storstad",
    "på landet/en avlägsen plats",
    "The Countryside/a remote place"
  ],
  "religion": [
    "4",
    "1",
    "2",
    "NA",
    "3",
    "I am spiritual but not religious",
    "Other (please specify)",
    "Christianity",
    "I am an atheist/agnostic",
    "Judaism",
    "Buddhism",
    "Hinduism",
    "Islam",
    "Chinese Traditional Religions (Taoism/Confucianism)",
    "Sikhism",
    "Ander, specificeer:",
    "Ik ben een Atheïst/Agnosticus",
    "Ik ben spiritueel maar niet religieus",
    "Christendom",
    "Sikhisme",
    "Mormón",
    "Evangélico",
    "Testigo de Jehová",
    "7",
    "0",
    "5",
    "9",
    "J'ai une spiritualité mais je ne suis pas religieux-euse",
    "Je suis athée / agnostique",
    "Christianisme",
    "Islam - Religion musulmane",
    "Bouddhisme",
    "Religions traditionnelles chinoises (Taoisme / Confucianisme)",
    "Autre (veuillez spécifier)",
    "Judaïsme",
    "J'ai une spiritualité mais je ne suis pas religieux(-euse)",
    "Hindouisme",
    "Islamisme",
    "6",
    "기독교",
    "나는 영적이지만 종교적이지 않다.",
    "나는 무신론자 / 불가 지론 자다.",
    "불교",
    "기타 (자세히 적어주십시오)",
    "8",
    "I am an atheist",
    "I am an agnostic",
    "o\tHrišćanstvo",
    "o\tDuhovna, ali ne i religiozna osoba",
    "o\tAteista/agnostik",
    "o\tBudizam",
    "o\tIslam",
    "Yo soy ateo(a)/agnóstico(a)",
    "Cristianismo",
    "Yo soy espiritual pero no religioso(a)",
    "Otra (especifique)",
    "Religiones chinas tradicionales (Taoismo/Confucianismo)",
    "Budismo",
    "Jag är andlig men inte religiös",
    "Kristendom",
    "Jag är ateist/agnostiker",
    "Annat (vänligen ange):",
    "Buddism",
    "Judendom",
    "3=Christianity",
    "4=Islam",
    "1=I am an atheist/agnostic",
    "2=I am spiritual but not religious"
  ],
  "sexual_orientation": [
    "5",
    "1",
    "2",
    "NA",
    "3",
    "4",
    "Heterosexual",
    "Mostly Homosexual/Gay/Lesbian",
    "Mostly Heterosexual",
    "Bisexual",
    "Homosexual/Gay/Lesbian",
    "Other, please specify",
    "Asexual",
    "Ander, specificeer:",
    "Heteroseksueel",
    "Voornamelijk heteroseksueel",
    "Biseksueel",
    "Voornamelijk homoseksueel",
    "Homoseksueel/Gay/Lesbisch",
    "Aseksueel",
    "6",
    "Surtout Hétérosexuel-le",
    "Hétérosexuel-le",
    "Asexuel-le",
    "Homosexuel-le / Gay / Lesbienne",
    "Bisexuel-le",
    "Surtout Homosexuel-le / Gay / Lesbienne",
    "Autre (veuillez préciser)",
    "Surtout Hétérosexuel(-le)",
    "Hétérosexuel(-le)",
    "Homosexuel(-le) / Gay / Lesbienne",
    "Bisexuel(-le)",
    "Asexuel(-le)",
    "Surtout Homosexuel(-le) / Gay / Lesbienne",
    "이성애자",
    "양성애자",
    "대체로 이성애자",
    "대체로 동성애 / 게이 / 레즈비언",
    "무성애자 (성적 취향이 없음)",
    "7",
    "o\tHeteroseksualne",
    "o\tHomoseksualne",
    "o\tUglavnom heteroseksualne",
    "o\tBiseksualne",
    "o\tAseksualne",
    "Mayormente Heterosexual",
    "Otro, especifique",
    "Mayormente Homosexual/Gay/Lesbiana",
    "Homosexual/Gay/Lesbiana",
    "Heterosexuell",
    "I huvudsak heterosexuell",
    "Homosexuell",
    "Bisexuell",
    "Annat, vänligen ange:",
    "Asexuell",
    "I huvudsak bisexuell/homosexuell",
    "1=Heterosexual",
    "6=Asexual",
    "3=Bisexual",
    "5=Homosexual/Gay/Lesbian"
  ],
  "immigration_backgrou": [
    "1",
    "NA",
    "4",
    "3",
    "2",
    "I was born in the United States",
    "I moved to the United States between age 6-14.",
    "I moved to the United States before age 6.",
    "I moved to the United States after age 18.",
    "I moved to the United States between age 15-18.",
    "I was born in Australia.",
    "I moved to Australia after age 18.",
    "I moved to Australia before age 6.",
    "I moved to Australia between age 6-14.",
    "I moved to Australia between age 15-18.",
    "Ik ben geboren in België",
    "Ik ben verhuisd naar België tussen mijn 6-14 jaar",
    "Ik ben verhuisd naar België na de leeftijd van 18 jaar",
    "Ik ben verhuisd naar België voor de leeftijd van 6 jaar",
    "Ik ben verhuisd naar België tussen mijn 15-18 jaar",
    "I was born in Canada.",
    "I moved to Canada before age 6.",
    "I moved to Canada between age 15-18.",
    "I moved to Canada between age 6-14.",
    "I moved to Canada after age 18.",
    "Je suis né-e en France",
    "Je suis arrivé-e en France entre l'âge de 6 et 14 ans.",
    "Je suis arrivé-e en France après 18 ans.",
    "Je suis arrivé-e en France avant l'âge de 6 ans.",
    "Je suis arrivé-e en France entre l'âge de 15 et 18 ans.",
    "Je suis né(e) en Suisse",
    "Je suis arrivé(e) en Suisse après 18 ans.",
    "Je suis arrivé(e) en Suisse avant l'âge de 6 ans.",
    "Je suis arrivé(e) en Suisse entre l'âge de 15 et 18 ans.",
    "Je suis arrivé(e) en Suisse entre l'âge de 6 et 14 ans.",
    "Je suis arrivé-e en Suisse après 18 ans.",
    "Je suis né-e en Suisse",
    "Je suis arrivé-e en Suisse entre l'âge de 15 et 18 ans.",
    "Je suis arrivé-e en Suisse avant l'âge de 6 ans.",
    "Je suis arrivé-e en Suisse entre l'âge de 6 et 14 ans.",
    "I moved to Ireland after age 18.",
    "I moved to Ireland before age 6.",
    "I was born in Ireland.",
    "I moved to Ireland between age 15-18.",
    "I moved to Ireland between age 6-14.",
    "I was born in the U.S.",
    "I moved to the U.S. after age 18.",
    "I moved to the U.S. between age 15-18.",
    "I moved to the U.S. between age 6-14.",
    "I moved to the U.S. before age 6.",
    "나는 한국에서 태어났다.",
    "나는 18살 이후에 한국으로 이사했다.",
    "나는 6살 이전에 한국으로 이사했다.",
    "I was born in Malaysia.",
    "I moved to Malaysia after age 18.",
    "I moved to Malaysia between age 15-18.",
    "I moved to Malaysia between age 6-14.",
    "Ik ben geboren in Nederland",
    "Ik ben verhuisd naar Nederland voor de leeftijd van 6 jaar",
    "Ik ben verhuisd naar Nederland na de leeftijd van 18 jaar",
    "Ik ben verhuisd naar Nederland tussen mijn 15-18 jaar",
    "Ik ben verhuisd naar Nederland tussen mijn 6-14 jaar",
    "I moved to New Zealand between age 6-14.",
    "I was born in New Zealand.",
    "I moved to New Zealand before age 6.",
    "I moved to New Zealand after age 18.",
    "I moved to New Zealand between age 15-18.",
    "o\tRođen/rođena sam u Srbiji.",
    "o\tDoselio/doselila sam se u Srbiju posle osamnaeste godine.",
    "o\tDoselio/doselila sam se u Srbiju između šeste i četrnaeste godine.",
    "o\tDoselio/doselila sam se u Srbiju pre šeste godine.",
    "I was born in Singapore.",
    "I moved to Singapore between age 6-14.",
    "I moved to Singapore before age 6.",
    "I moved to Singapore after age 18.",
    "I moved to Singapore between age 15-18.",
    "Nací en España",
    "Me mudé a España antes de los 6 años.",
    "Me mudé a España después de los 18 años.",
    "Me mudé a España entre los 6-14 años.",
    "Jag föddes i Sverige",
    "Jag flyttade till Sverige innan 6 års ålder",
    "Jag flyttade till Sverige mellan 6-14 års ålder",
    "Jag flyttade till Sverige efter 18 års ålder",
    "Jag flyttade till Sverige mellan 15-18 års ålder",
    "1= I was born in Tanzania",
    "5=I moved to Tanzania after age 18",
    "I was born in the UK.",
    "I moved to the UK after age 18.",
    "I moved to the UK between age 15-18.",
    "I moved to the UK before age 6.",
    "I moved to the UK between age 6-14.",
    "I was born in the U.S..",
    "I was born in the United States."
  ],
  "migration_background": [
    "1",
    "3",
    "NA",
    "2",
    "b) I was born in the United States, but one of my parents or both of my parents were born outside of the United States",
    "a) I was born in the United States to parents who are also born in the United States.",
    "c) Born in a country that is not the United States",
    "a) I was born in Australia to parents who are also born in Australia.",
    "b) I was born in Australia, but one of my parents or both of my parents were born outside of Australia",
    "c) Born in a country that is not Australia",
    "Ik ben geboren in België en mijn beide ouders ook",
    "Ik ben geboren in België en één of beide van mijn ouders is/zijn geboren buiten België",
    "West Europa",
    "Zuid Amerika",
    "Ik ben buiten België geboren",
    "VS",
    "Rest van Afrika",
    "Azië",
    "Indien antwoordoptie 2 of 3 specifieer dan van welke regio: Oost Europa",
    "Midden Oosten",
    "Noord Afrika",
    "Canada",
    "a) I was born in Canada to parents who are also born in Canada.",
    "b) I was born in Canada, but one of my parents or both of my parents were born outside of Canada",
    "c) Born in a country that is not Canada",
    "Je suis né-e en France de parents également nés en France.",
    "Je suis né-e dans un pays autre que la France :",
    "Je suis né-e en France,  mais un de mes parents est né (ou les deux sont nés) ailleurs qu'en France",
    "b) Je suis né(e) en Suisse, mais un de mes parents est né (ou les deux sont nés) ailleurs qu'en Suisse",
    "c) Je suis né(e) dans un pays autre que la Suisse :",
    "a) Je suis né(e) en Suisse de parents également nés en Suisse.",
    "Je suis né-e dans un pays autre que la Suisse :",
    "Je suis né-e en Suisse, mais un de mes parents est né (ou les deux sont nés) ailleurs qu'en Suisse",
    "Je suis né-e en Suisse de parents également nés en Suisse.",
    "c) Born in a country that is not Ireland",
    "a) I was born in Ireland to parents who are also born in Ireland.",
    "b) I was born in Canada, but one of my parents or both of my parents were born outside of Ireland",
    "a) I was born in the U.S. to parents who are also born in the U.S.",
    "b) I was born in the U.S., but one of my parents or both of my parents were born outside of the U.S.",
    "c) Born in a country that is not the U.S.",
    "a) 나는 한국에서 태어났고, 부모님도 모두 한국에서 태어나셨다.",
    "c) 한국이 아닌 다른 나라에서 태어났다 (구체적으로 적어주시기 바랍니다).",
    "b) I was born in Malaysia, but one of my parents or both of my parents were born outside of Malaysia",
    "a) I was born in Malaysia to parents who are also born in Malaysia.",
    "c) Born in a country that is not Malaysia",
    "c) Born in a country that is not New Zealand",
    "b) I was born in New Zealand, but one of my parents or both of my parents were born outside of New Zealand",
    "a) I was born in New Zealand to parents who are also born in New Zealand.",
    "a) Rođen/rođena sam u Srbiji kao i oba moja roditelja.",
    "c) Nisam rođen/rođena u Srbiji, već u drugoj državi.",
    "b) Rođen/rođena sam u Srbiji, ali su jedan ili oba moja roditelja rođeni van Srbije.",
    "a) I was born in Singapore to parents who are also born in Singapore.",
    "c) Born in a country that is not Singapore",
    "b) I was born in Singapore, but one of my parents or both of my parents were born outside of Singapore.",
    "a) Nací en España de padre y madre nacidos también en España.",
    "c) Nací en un país que no es España (Por favor, especifícalo)",
    "b)  Nací en España, pero uno de mis progenitores ambos nacieron fuera de España",
    "a) Båda mina föräldrar och jag föddes i Sverige",
    "c) Jag föddes i ett annat land",
    "b) Jag föddes i Sverige, men en eller båda mina föräldrar föddes i ett annat land",
    "6",
    "7",
    "5",
    "d) Born in a country that is not Canada",
    "c) I was born in Canada, but one of my parents was born outside of Canada (please specify)",
    "b) I was born in Canada, but both my parents were born outside of Canada (please specify)",
    "b) I was born in Canada, but both of my parents were born outside of Canada",
    "c) I was born in Canada, but one of my parents was born outside of Canada",
    "1= I was born in Tanzania to parents who are also born in Tanzania.",
    "a) I was born in the UK to parents who are also born in the UK.",
    "b) I was born in the UK, but one of my parents or both of my parents were born outside of the UK",
    "c) Born in a country that is not the UK",
    "a) I was born in the U.S. to parents who are also born in the U.S..",
    "b) I was born in the United States, but one of my parents or both of my parents were born outside of the United States."
  ],
  "ethnic_background": [
    "1",
    "NA",
    "7",
    "4",
    "South American/Hispanic/Latino",
    "White/Caucasian/European",
    "Aboriginal/Native/First Nation",
    "South Asian",
    "Arabic/Middle Eastern/North African",
    "Black/African American",
    "East Asian & Pacific Islander",
    "Caribbean/South Islands",
    "Central or Southern African",
    "Black/African American/Canadian",
    "Black/African American/Australian",
    "Belgisch",
    "Anders, namelijk:",
    "Nederlands",
    "Pools",
    "Italiaans",
    "Turks",
    "Marokkaans",
    "Black/African",
    "2",
    "0",
    "5",
    "6",
    "Meztizo/a",
    "Mixed race",
    "Indian",
    "Caucasian",
    "afrodescendant",
    "Central or Southern Africa",
    "Eastern Africa",
    "Blanc/Caucasien/Européen",
    "Arabe/Moyen-Oriental/Nord-Africain",
    "Sud-Américain/Hispanique/Latino",
    "Noir/DOM-TOM ou Afro-Français ou Afro-Européen ou Afro-Américain ou Afro-Canadien",
    "Caraïbes/Océanie",
    "Sud-Asiatique",
    "Est-Asiatique & Insulaire du Pacifique",
    "Centre- ou Sud-Africain",
    "Noir/Afro-Américain ou Afro-Canadien",
    "동아시아 또는 태평양 섬 주민",
    "백인/ 유럽인",
    "남아시아인",
    "원주민",
    "Lebanese",
    "Dual nationality (Lebanese plus other nationality-please specify",
    "Other (please specify)",
    "Ik ben geboren in Nederland en mijn beide ouders ook",
    "Midden Oosten",
    "Ik ben geboren in Nederland en één of beide van mijn ouders is/zijn geboren buiten Nederland",
    "West Europa",
    "Rest van Afrika",
    "Azië",
    "Ik ben buiten Nederland geboren",
    "Indien antwoordoptie 2 of 3 specifieer dan van welke regio: Oost Europa",
    "Noord Afrika",
    "White/Caucasian/European/Pākehā",
    "Pasifika",
    "East Asian",
    "Māori",
    "Black/African New Zealander",
    "Other Aboriginal/ Indigenous",
    "Alta (menționați care...)",
    "o\tBelac/Evropljanin",
    "o\tIstočna Azija/Pacifička ostrva",
    "Blanco(a)/Caucásico(a)/Europeo(a) del Este",
    "Caribeño(a)/Islas del Sur",
    "Asiático/a",
    "Sudamericano(a)/Hispano(a)/Latino(a)",
    "Indígena/Aborigen/Nativo(a) Americano/Pueblo Originario",
    "Negro(a)/ Africano(a)",
    "Árabe/Oriente Medio/ Norteafricano(a)",
    "Vit/Kaukasisk/europeisk",
    "Sydamerikan/Latinamerikan/Latino",
    "Svart/Afrikansk amerikansk/kanadensisk",
    "Från centrala eller södra Afrika",
    "Från Östasien & Stillahavsområdet",
    "Arab/från östra eller norra Afrika",
    "Från Sydasien",
    "4=Black/African",
    "5=Caribbean/South Island",
    "7=Arabic/Middle Eastern/Northing African",
    "Black/African American/American",
    "American Indian or Alaska Native",
    "Latino/Hispanic/South or Central American",
    "Black/African American/"
  ],
  "marital_status": [
    "1",
    "2",
    "NA",
    "3",
    "single (never married)",
    "in a committed non-marital relationship",
    "divorced",
    "married/ common law/domestic partnership",
    "Alleenstaand (nooit getrouwd)",
    "In een toegewijde, ongehuwde relatie",
    "Getrouwd/wettelijk samenwonend",
    "married/common law/domestic partnership",
    "married/ common law/ domestic partnership",
    "4",
    "engagé-e dans une relation de couple (non-marié)",
    "célibataire (jamais marié-e)",
    "marié-e/en partenariat enregistré",
    "divorcé(e)",
    "engagé(e) dans une relation de couple (non-marié)",
    "marié(e)/en partenariat enregistré",
    "divorcé-e",
    "7",
    "21",
    "미혼 (결혼해본 적 없음)",
    "미혼이지만 진지한 관계",
    "결혼/사실혼 관계",
    "o\tU stabilnoj vezi, ali ne u braku",
    "o\tSlobodan/slobodna, nikada se nisam ženio/udavala",
    "o\tU braku ili vanbračnoj zajednici",
    "o\tRazveden/razvedena",
    "Soltero/a (nunca casado/a)",
    "En una relación no matrimonial comprometida",
    "Casado/a o pareja de hecho",
    "Divorciado/a",
    "i ett seriöst förhållande men ej gift",
    "gift/registrerat partnerskap",
    "singel (aldrig gift)",
    "skild",
    "In a committed non-marital relationship"
  ]
}

